riguima_stopwatch/__init__.py
riguima_stopwatch/main.py
riguima_stopwatch/stopwatch.tcss
riguima_stopwatch-0.1.0.dist-info/METADATA
riguima_stopwatch-0.1.0.dist-info/WHEEL
riguima_stopwatch-0.1.0.dist-info/entry_points.txt
riguima_stopwatch-0.1.0.dist-info/RECORD
